simple_gyro.py
circuitpython_simple_gyro-0.1.0.dist-info/LICENSE
circuitpython_simple_gyro-0.1.0.dist-info/METADATA
circuitpython_simple_gyro-0.1.0.dist-info/WHEEL
circuitpython_simple_gyro-0.1.0.dist-info/top_level.txt
circuitpython_simple_gyro-0.1.0.dist-info/RECORD
